reprepbuild/__init__.py
reprepbuild/__main__.py
reprepbuild/_version.py
reprepbuild/command.py
reprepbuild/config.py
reprepbuild/generator.py
reprepbuild/helpers.py
reprepbuild/nameglob.py
reprepbuild/repeat.py
reprepbuild/utils.py
reprepbuild/builtin/__init__.py
reprepbuild/builtin/check_hrefs.py
reprepbuild/builtin/latex.py
reprepbuild/builtin/mupdf.py
reprepbuild/builtin/python_script.py
reprepbuild/builtin/render.py
reprepbuild/builtin/shell_script.py
reprepbuild/builtin/transform.py
reprepbuild/builtin/zip.py
reprepbuild/scripts/__init__.py
reprepbuild/scripts/check_hrefs.py
reprepbuild/scripts/generator.py
reprepbuild/scripts/latex.py
reprepbuild/scripts/latex_flat.py
reprepbuild/scripts/manifest.py
reprepbuild/scripts/markdown_pdf.py
reprepbuild/scripts/pdf_add_notes.py
reprepbuild/scripts/pdf_normalize.py
reprepbuild/scripts/pdf_nup.py
reprepbuild/scripts/pdf_raster.py
reprepbuild/scripts/python_script.py
reprepbuild/scripts/render.py
reprepbuild/scripts/shell_script.py
reprepbuild/scripts/zip_latex.py
reprepbuild/scripts/zip_manifest.py
reprepbuild/scripts/zip_plain.py
RepRepBuild-1.14.0.dist-info/COPYING
RepRepBuild-1.14.0.dist-info/METADATA
RepRepBuild-1.14.0.dist-info/WHEEL
RepRepBuild-1.14.0.dist-info/entry_points.txt
RepRepBuild-1.14.0.dist-info/top_level.txt
RepRepBuild-1.14.0.dist-info/RECORD
