Metadata-Version: 2.1
Name: RepRepBuild
Version: 1.14.0
Summary: Build tool for Reproducible Reporting
Author-email: Toon Verstraelen <toon.verstraelen@ugent.be>
License: GNU GENERAL PUBLIC LICENSE
Project-URL: Issues, https://github.com/reproducible-reporting/reprepbuild/issues
Project-URL: Source, https://github.com/reproducible-reporting/reprepbuild/
Project-URL: Changelog, https://github.com/reproducible-reporting/reprepbuild/blob/main/CHANGELOG.md
Classifier: Environment :: Console
Classifier: Intended Audience :: Science/Research
Classifier: Intended Audience :: Education
Classifier: Framework :: Matplotlib
Classifier: License :: OSI Approved :: GNU General Public License v3 or later (GPLv3+)
Classifier: Natural Language :: English
Classifier: Operating System :: POSIX
Classifier: Operating System :: MacOS
Classifier: Programming Language :: Python :: 3
Classifier: Topic :: Scientific/Engineering
Classifier: Topic :: Education :: Computer Aided Instruction (CAI)
Classifier: Topic :: Text Processing
Classifier: Topic :: Text Processing :: Markup :: LaTeX
Requires-Python: >=3.11
License-File: COPYING
Requires-Dist: attrs
Requires-Dist: beautifulsoup4
Requires-Dist: bibsane
Requires-Dist: jinja2
Requires-Dist: markdown
Requires-Dist: markdown-katex
Requires-Dist: ninja
Requires-Dist: numpy
Requires-Dist: parse
Requires-Dist: pymupdf >=1.23.16
Requires-Dist: pyyaml
Requires-Dist: requests
Requires-Dist: scipy
Requires-Dist: setuptools
Requires-Dist: tqdm
Requires-Dist: watchdog
Requires-Dist: weasyprint
